{
  "$schema": "https://biomejs.dev/schemas/1.9.4/schema.json",
  "vcs": {
    "enabled": false,
    "clientKind": "git",
    "useIgnoreFile": false
  },
  "files": {
    "ignoreUnknown": false,
    "include": ["apps/**/*.{js,jsx,ts,tsx}", "packages/**/*.{js,jsx,ts,tsx}"],
    "ignore": []
  },
  "formatter": {
    "enabled": true,
    "indentStyle": "space"
  },
  "organizeImports": {
    "enabled": true
  },
  "linter": {
    "enabled": true,
    "rules": {
      "recommended": true,
      "nursery": {
        "useSortedClasses": "error"
      }
    }
  },
  "javascript": {
    "formatter": {
      "quoteStyle": "double"
    }
  }
}
